Metadata-Version: 2.1
Name: mobio-admin-sdk
Version: 1.0.6
Summary: Mobio admin SDK
Home-page: https://github.com/mobiovn
Author: MOBIO
Author-email: contact@mobio.vn
License: MIT
Project-URL: Source, https://github.com/mobiovn
Keywords: mobio,admin sdk,verify token
Classifier: Development Status :: 3 - Alpha
Classifier: Intended Audience :: Developers
Classifier: Topic :: Software Development :: Build Tools
Classifier: License :: OSI Approved :: MIT License
Classifier: Programming Language :: Python :: 3
Classifier: Programming Language :: Python :: 3.6
Classifier: Programming Language :: Python :: 3.7
Classifier: Programming Language :: Python :: 3.8
Classifier: Programming Language :: Python :: 3.9
Classifier: Programming Language :: Python :: 3 :: Only
Requires-Python: >=3
Requires-Dist: Flask
Requires-Dist: m-caching
Requires-Dist: m-singleton
Requires-Dist: python-jose
Requires-Dist: m-cipher
Requires-Dist: m-kafka-sdk-v2
Requires-Dist: redis
Requires-Dist: pycryptodome
Requires-Dist: mobio-license-sdk
